<?xml version="1.0" encoding="UTF-8"?>
<Export generator="Cache" version="25">
<Class name="Custom.SWARH.HIPS.ws.tns.duration">
<Description>
Created from: http://sahipsh00.swarh.net:50500/HIPSServer_TEST/HIPS.Service.PCEHRService.svc?xsd=xsd1</Description>
<ProcedureBlock>1</ProcedureBlock>
<Super>%String</Super>
<TimeCreated>64371,57027.223884</TimeCreated>

<Parameter name="ATTRIBUTEQUALIFIED">
<Default>1</Default>
</Parameter>

<Parameter name="ELEMENTQUALIFIED">
<Default>1</Default>
</Parameter>

<Parameter name="MAXLEN">
</Parameter>

<Parameter name="NAMESPACE">
<Default>http://schemas.microsoft.com/2003/10/Serialization/</Default>
</Parameter>

<Parameter name="XMLPATTERN">
<Default>\-?P(\d*D)?(T(\d*H)?(\d*M)?(\d*(\.\d*)?S)?)?</Default>
</Parameter>
</Class>
</Export>
